kol/__init__.py
kol/ast.py
kol/builtin.py
kol/bytecode.py
kol/cli.py
kol/compiler.py
kol/frame.py
kol/func.py
kol/lexer.py
kol/none.py
kol/parser.py
kol/struct.py
kol/token.py
kol/vm.py
korean_lang-1.0.1.dist-info/licenses/LICENSE
korean_lang-1.0.1.dist-info/METADATA
korean_lang-1.0.1.dist-info/WHEEL
korean_lang-1.0.1.dist-info/entry_points.txt
korean_lang-1.0.1.dist-info/top_level.txt
korean_lang-1.0.1.dist-info/RECORD
