Metadata-Version: 2.4
Name: korean-lang
Version: 1.0.1
Summary: korean language
Author-email: smc0478 <smc0478@naver.com>
Requires-Python: >=3.8
License-File: LICENSE
Dynamic: license-file
